libcasm/include/casm/monte/BasicStatistics.hh
libcasm/include/casm/monte/Conversions.hh
libcasm/include/casm/monte/MTRandEngine.hh
libcasm/include/casm/monte/MethodLog.hh
libcasm/include/casm/monte/RandomNumberGenerator.hh
libcasm/include/casm/monte/ValueMap.hh
libcasm/include/casm/monte/definitions.hh
libcasm/include/casm/monte/checks/CompletionCheck.hh
libcasm/include/casm/monte/checks/ConvergenceCheck.hh
libcasm/include/casm/monte/checks/CutoffCheck.hh
libcasm/include/casm/monte/checks/EquilibrationCheck.hh
libcasm/include/casm/monte/checks/io/json/CompletionCheck_json_io.hh
libcasm/include/casm/monte/checks/io/json/ConvergenceCheck_json_io.hh
libcasm/include/casm/monte/checks/io/json/CutoffCheck_json_io.hh
libcasm/include/casm/monte/checks/io/json/EquilibrationCheck_json_io.hh
libcasm/include/casm/monte/events/OccCandidate.hh
libcasm/include/casm/monte/events/OccEvent.hh
libcasm/include/casm/monte/events/OccEventProposal.hh
libcasm/include/casm/monte/events/OccLocation.hh
libcasm/include/casm/monte/events/io/OccCandidate_json_io.hh
libcasm/include/casm/monte/events/io/OccCandidate_stream_io.hh
libcasm/include/casm/monte/io/json/ValueMap_json_io.hh
libcasm/include/casm/monte/ising_cpp/basic_semigrand_canonical.hh
libcasm/include/casm/monte/ising_cpp/complete_semigrand_canonical.hh
libcasm/include/casm/monte/ising_cpp/model.hh
libcasm/include/casm/monte/methods/basic_occupation_metropolis.hh
libcasm/include/casm/monte/methods/kinetic_monte_carlo.hh
libcasm/include/casm/monte/methods/metropolis.hh
libcasm/include/casm/monte/methods/nfold.hh
libcasm/include/casm/monte/methods/occupation_metropolis.hh
libcasm/include/casm/monte/misc/BasicStructureTools.hh
libcasm/include/casm/monte/misc/LexicographicalCompare.hh
libcasm/include/casm/monte/misc/math.hh
libcasm/include/casm/monte/misc/memory_used.hh
libcasm/include/casm/monte/misc/polymorphic_method_json_io.hh
libcasm/include/casm/monte/run_management/Results.hh
libcasm_monte-2.2.0.dist-info/licenses/LICENSE
libcasm_monte-2.2.0.dist-info/METADATA
libcasm_monte-2.2.0.dist-info/WHEEL
libcasm_monte-2.2.0.dist-info/top_level.txt
libcasm_monte-2.2.0.dist-info/RECORD
