Metadata-Version: 2.4
Name: libcasm-monte
Version: 2.2.0
Summary: CASM building blocks for Monte Carlo simulations
Author-email: CASM developers <casm-developers@lists.engr.ucsb.edu>
License-Expression: LGPL-2.1-or-later
Project-URL: Homepage, https://prisms-center.github.io/CASMcode_docs/
Project-URL: Repository, https://github.com/prisms-center/CASMcode_monte
Classifier: Development Status :: 5 - Production/Stable
Classifier: Programming Language :: Python :: 3
Classifier: Programming Language :: C++
Classifier: Topic :: Scientific/Engineering
Requires-Python: <3.14,>=3.9
License-File: LICENSE
Requires-Dist: libcasm-global>=2.2.0
Requires-Dist: libcasm-xtal>=2.2.0
Requires-Dist: libcasm-composition>=2.2.0
Requires-Dist: numpy
Dynamic: license-file
